{
 "custom_fields": [],
 "custom_perms": [],
 "doctype": "Request for Quotation",
 "links": [],
 "property_setters": [
  {
   "_assign": null,
   "_comments": null,
   "_liked_by": null,
   "_user_tags": null,
   "creation": "2024-09-11 13:02:53.727331",
   "default_value": null,
   "doc_type": "Request for Quotation",
   "docstatus": 0,
   "doctype_or_field": "DocField",
   "field_name": "email_template",
   "idx": 0,
   "is_system_generated": 0,
   "modified": "2024-09-11 13:02:53.727331",
   "modified_by": "Administrator",
   "module": null,
   "name": "Request for Quotation-email_template-default",
   "owner": "Administrator",
   "property": "default",
   "property_type": "Text",
   "row_name": null,
   "value": "Dispatch Notification"
  },
  {
   "_assign": null,
   "_comments": null,
   "_liked_by": null,
   "_user_tags": null,
   "creation": "2024-09-11 13:07:15.581414",
   "default_value": null,
   "doc_type": "Request for Quotation",
   "docstatus": 0,
   "doctype_or_field": "DocField",
   "field_name": "email_template",
   "idx": 0,
   "is_system_generated": 0,
   "modified": "2024-09-11 13:07:15.581414",
   "modified_by": "Administrator",
   "module": null,
   "name": "Request for Quotation-email_template-hidden",
   "owner": "Administrator",
   "property": "hidden",
   "property_type": "Check",
   "row_name": null,
   "value": "1"
  },
  {
   "_assign": null,
   "_comments": null,
   "_liked_by": null,
   "_user_tags": null,
   "creation": "2024-09-11 13:07:15.640051",
   "default_value": null,
   "doc_type": "Request for Quotation",
   "docstatus": 0,
   "doctype_or_field": "DocField",
   "field_name": "html_llwp",
   "idx": 0,
   "is_system_generated": 0,
   "modified": "2024-09-11 13:07:15.640051",
   "modified_by": "Administrator",
   "module": null,
   "name": "Request for Quotation-html_llwp-hidden",
   "owner": "Administrator",
   "property": "hidden",
   "property_type": "Check",
   "row_name": null,
   "value": "1"
  },
  {
   "_assign": null,
   "_comments": null,
   "_liked_by": null,
   "_user_tags": null,
   "creation": "2024-09-11 13:06:36.351396",
   "default_value": null,
   "doc_type": "Request for Quotation",
   "docstatus": 0,
   "doctype_or_field": "DocField",
   "field_name": "message_for_supplier",
   "idx": 0,
   "is_system_generated": 0,
   "modified": "2024-09-11 13:06:36.351396",
   "modified_by": "Administrator",
   "module": null,
   "name": "Request for Quotation-message_for_supplier-default",
   "owner": "Administrator",
   "property": "default",
   "property_type": "Text",
   "row_name": null,
   "value": "Ok"
  },
  {
   "_assign": null,
   "_comments": null,
   "_liked_by": null,
   "_user_tags": null,
   "creation": "2024-09-11 13:06:44.024294",
   "default_value": null,
   "doc_type": "Request for Quotation",
   "docstatus": 0,
   "doctype_or_field": "DocField",
   "field_name": "message_for_supplier",
   "idx": 0,
   "is_system_generated": 0,
   "modified": "2024-09-11 13:06:44.024294",
   "modified_by": "Administrator",
   "module": null,
   "name": "Request for Quotation-message_for_supplier-hidden",
   "owner": "Administrator",
   "property": "hidden",
   "property_type": "Check",
   "row_name": null,
   "value": "1"
  },
  {
   "_assign": null,
   "_comments": null,
   "_liked_by": null,
   "_user_tags": null,
   "creation": "2024-06-28 16:11:20.610056",
   "default_value": null,
   "doc_type": "Request for Quotation",
   "docstatus": 0,
   "doctype_or_field": "DocField",
   "field_name": "naming_series",
   "idx": 0,
   "is_system_generated": 0,
   "modified": "2024-09-10 16:54:28.734644",
   "modified_by": "Administrator",
   "module": "",
   "name": "Request for Quotation-naming_series-options",
   "owner": "Administrator",
   "property": "options",
   "property_type": "Text",
   "row_name": null,
   "value": "PUR-RFQ-.YYYY.-"
  },
  {
   "_assign": null,
   "_comments": null,
   "_liked_by": null,
   "_user_tags": null,
   "creation": "2024-09-11 13:08:09.156077",
   "default_value": null,
   "doc_type": "Request for Quotation",
   "docstatus": 0,
   "doctype_or_field": "DocField",
   "field_name": "preview",
   "idx": 0,
   "is_system_generated": 0,
   "modified": "2024-09-11 13:08:09.156077",
   "modified_by": "Administrator",
   "module": null,
   "name": "Request for Quotation-preview-hidden",
   "owner": "Administrator",
   "property": "hidden",
   "property_type": "Check",
   "row_name": null,
   "value": "1"
  },
  {
   "_assign": null,
   "_comments": null,
   "_liked_by": null,
   "_user_tags": null,
   "creation": "2024-09-11 13:07:15.702507",
   "default_value": null,
   "doc_type": "Request for Quotation",
   "docstatus": 0,
   "doctype_or_field": "DocField",
   "field_name": "send_attached_files",
   "idx": 0,
   "is_system_generated": 0,
   "modified": "2024-09-11 13:07:15.702507",
   "modified_by": "Administrator",
   "module": null,
   "name": "Request for Quotation-send_attached_files-hidden",
   "owner": "Administrator",
   "property": "hidden",
   "property_type": "Check",
   "row_name": null,
   "value": "1"
  },
  {
   "_assign": null,
   "_comments": null,
   "_liked_by": null,
   "_user_tags": null,
   "creation": "2024-09-11 13:07:15.766675",
   "default_value": null,
   "doc_type": "Request for Quotation",
   "docstatus": 0,
   "doctype_or_field": "DocField",
   "field_name": "send_document_print",
   "idx": 0,
   "is_system_generated": 0,
   "modified": "2024-09-11 13:07:15.766675",
   "modified_by": "Administrator",
   "module": null,
   "name": "Request for Quotation-send_document_print-hidden",
   "owner": "Administrator",
   "property": "hidden",
   "property_type": "Check",
   "row_name": null,
   "value": "1"
  }
 ],
 "sync_on_migrate": 1
}